{
  "raw_analysis": "```json\n{\n  \"temporal_anomalies\": [\n    {\n      \"text\": \"Bitcoin holds steady near $66,000 despite a broader market pullback triggered by concerns over quantum computing risks\",\n      \"future_reference\": \"Quantum computing vulnerability pricing into current crypto derivatives\",\n      \"confidence\": 0.82,\n      \"platform\": \"Benzinga/Financial Media\",\n      \"timeframe\": \"LT\"\n    },\n    {\n      \"text\": \"Inside The Viral 2026 Resurgence Of Ripple's 'Hypothetical' Listing Fee Story\",\n      \"future_reference\": \"Retroactive narrative building masking 2023 exchange dynamics in 2026 market cycle\",\n      \"confidence\": 0.75,\n      \"platform\": \"Benzinga\",\n      \"timeframe\": \"ST\"\n    },\n    {\n      \"text\": \"Ethereum May Get 'Flipped' in 2026 Without Bitcoin's Involvement\",\n      \"future_reference\": \"Stablecoin market cap overtaking smart-contract platform valuation within current calendar year\",\n      \"confidence\": 0.68,\n      \"platform\": \"CoinTelegraph/Polymarket\",\n      \"timeframe\": \"IM\"\n    },\n    {\n      \"text\": \"Trump threatens to 'obliterate' Iran's power plants, oil wells and Kharg Island if a deal isn't reached\",\n      \"future_reference\": \"Pre-announced kinetic targeting of energy infrastructure driving >$100 oil & risk-off flows\",\n      \"confidence\": 0.88,\n      \"platform\": \"CoinDesk/Benzinga\",\n      \"timeframe\": \"IM\"\n    },\n    {\n      \"text\": \"XRP Is Down 60%... What the Next 4 Years Could Realistically Look Like\",\n      \"future_reference\": \"Extended consolidation phase projected by mainstream finance, ignoring cyclical reset patterns\",\n      \"confidence\": 0.60,\n      \"platform\": \"Nasdaq/Motley Fool\",\n      \"timeframe\": \"LT\"\n    }\n  ],\n  \"memetic_lifecycle\": [\n    {\n      \"pattern\": \"AI-Integrated Blockchain Security\",\n      \"stage\": 3,\n      \"stage_name\": \"Momentum\",\n      \"evidence\": \"Ripple implementing AI adversarial testing across XRPL pull requests; Bittensor AI token up 57%; transition from experimental to institutional utility standard.\",\n      \"timeframe\": \"ST\"\n    },\n    {\n      \"pattern\": \"Crypto as Geopolitical Safe-Haven\",\n      \"stage\": 4,\n      \"stage_name\": \"Critique\",\n      \"evidence\": \"Narrative fracturing as BTC correlates with risk-off equity selloffs during Iran tensions; 'digital gold' thesis challenged by macro liquidations.\",\n      \"timeframe\": \"IM\"\n    },\n    {\n      \"pattern\": \"Institutional XRP Accumulation vs Retail Bearishness\",\n      \"stage\": 5,\n      \"stage_name\": \"Integration\",\n      \"evidence\": \"Whale inflows ($120M+ tokens), Goldman Sachs ETF exposure ($152M), and MAS sandbox testing normalizing despite -60% retail price sentiment.\",\n      \"timeframe\": \"ST\"\n    },\n    {\n      \"pattern\": \"Gamified Trading & Simulation\",\n      \"stage\": 2,\n      \"stage_name\": \"Excitement\",\n      \"evidence\": \"Emergence of 'Oracle Gym' powered by Pyth Network; shift from paper trading to gamified, real-data replay environments for retail education.\",\n      \"timeframe\": \"IM\"\n    }\n  ],\n  \"archetypes\": [\n    {\n      \"name\": \"The Catalyst\",\n      \"frequency\": 8,\n      \"examples\": [\n        \"CLARITY Act stuck in Senate as final XRP catalyst\",\n        \"Trump/Iran ceasefire negotiations driving immediate price action\",\n        \"Hashdex diversified crypto ETF options debut on Nasdaq\"\n      ]\n    },\n    {\n      \"name\": \"The Herald\",\n      \"frequency\": 6,\n      \"examples\": [\n        \"Analysts flagging 'late-stage correction' and 'strong buy signals'\",\n        \"Polymarket odds predicting Tether 'Flippening'\",\n        \"RSI/MACD indicators flashing historic reversal signals\"\n      ]\n    },\n    {\n      \"name\": \"The Shadow\",\n      \"frequency\": 5,\n      \"examples\": [\n        \"Quantum computing security concerns triggering $268M liquidations\",\n        \"Hidden whale accumulation countering public bearish sentiment\",\n        \"78% leverage flush signaling speculative position unwinding\"\n      ]\n    },\n    {\n      \"name\": \"The Trickster\",\n      \"frequency\": 4,\n      \"examples\": [\n        \"Viral 'hypothetical' exchange listing fee story resurfacing\",\n        \"Options-expiry relief rallies immediately fading into macro selloffs\",\n        \"Record Q1 corporate revenue paired with asset price drops\"\n      ]\n    },\n    {\n      \"name\": \"The Wise Elder\",\n      \"frequency\": 3,\n      \"examples\": [\n        \"Long-term holders defending $66k-$67k BTC range\",\n        \"Garlinghouse's 'North Star' utility vision over short-term price\",\n        \"50-day range-bound accumulation signaling smart money positioning\"\n      ]\n    }\n  ],\n  \"metaphors\": [\n    {\n      \"term\": \"Running low on fuel\",\n      \"context\": \"Crypto Daybook describing BTC/ETH bounce sustainability\",\n      \"spread_score\": 0.71,\n      \"is_emerging\": false\n    },\n    {\n      \"term\": \"Gamified Arena\",\n      \"context\": \"Oracle Gym platform using Pyth Network for flash crash simulation\",\n      \"spread_score\": 0.65,\n      \"is_emerging\": true\n    },\n    {\n      \"term\": \"Cratered / Defend Support / Unstable Setup\",\n      \"context\": \"Military/terrain language applied to XRP price action and leverage positioning\",\n      \"spread_score\": 0.89,\n      \"is_emerging\": false\n    },\n    {\n      \"term\": \"North Star\",\n      \"context\": \"Corporate utility and long-term protocol direction vs short-term volatility\",\n      \"spread_score\": 0.58,\n      \"is_emerging\": false\n    },\n    {\n      \"term\": \"Flood back / Liquidation Wave\",\n      \"context\": \"Capital rotation narratives and forced deleveraging mechanics\",\n      \"spread_score\": 0.76,\n      \"is_emerging\": false\n    }\n  ],\n  \"contradictions\": [\n    {\n      \"narrative\": \"Institutional adoption signals strength (ETF inflows, Goldman exposure, MAS sandbox)\",\n      \"counter_narrative\": \"Asset prices continue to decline (-60% XRP, -3.7% BTC daily drops, fear gauge at 26)\",\n      \"tension_level\": \"high\"\n    },\n    {\n      \"narrative\": \"Bitcoin as geopolitical safe-haven during Middle East tensions\",\n      \"counter_narrative\": \"BTC correlates with risk-off equity selloffs and macro liquidations\",\n      \"tension_level\": \"high\"\n    },\n    {\n      \"narrative\": \"Record Q1 corporate revenue and tripled prime brokerage volume for Ripple\",\n      \"counter_narrative\": \"XRP token price drops 10-23% in same period, decoupling utility from asset value\",\n      \"tension_level\": \"medium\"\n    },\n    {\n      \"narrative\": \"AI-driven security upgrades preparing ledgers for institutional scale\",\n      \"counter_narrative\": \"Quantum computing vulnerability fears triggering immediate market sell-offs\",\n      \"tension_level\": \"medium\"\n    },\n    {\n      \"narrative\": \"Analysts calling 'final downside' and 'imminent 30% breakout'\",\n      \"counter_narrative\": \"Mainstream finance projecting multi-year consolidation and 'rebound may never come'\",\n      \"tension_level\": \"medium\"\n    }\n  ],\n  \"future_leaks\": [\n    {\n      \"indicator\": \"AI-assisted adversarial testing becoming mandatory for public ledger updates\",\n      \"confidence\": 0.85,\n      \"timeline\": \"ST (4-6 months)\",\n      \"supporting_evidence\": [\n        \"Ripple rolling out AI code scanning for every pull request\",\n        \"Automated stress-testing for institutional tokenization scaling\",\n        \"Cross-platform coverage in tech and finance media\"\n      ]\n    },\n    {\n      \"indicator\": \"Stablecoin market cap dominance challenging smart-contract platform valuations\",\n      \"confidence\": 0.72,\n      \"timeline\": \"ST (3-9 months)\",\n      \"supporting_evidence\": [\n        \"Polymarket 59% odds of Tether flipping ETH in 2026\",\n        \"Shift from yield-bearing assets to settlement-layer utility\",\n        \"Institutional focus on trade finance tokenization over speculative DeFi\"\n      ]\n    },\n    {\n      \"indicator\": \"Quantum computing vulnerability pricing into crypto derivatives and ETF structures\",\n      \"confidence\": 0.78,\n      \"timeline\": \"LT (12-18 months)\",\n      \"supporting_evidence\": [\n        \"Quantum security concerns triggering $268M liquidations\",\n        \"Mainstream financial media treating quantum risk as immediate macro factor\",\n        \"Lack of post-quantum cryptographic migration in legacy chains\"\n      ]\n    },\n    {\n      \"indicator\": \"Tokenization of real-world trade finance bypassing traditional SWIFT corridors\",\n      \"confidence\": 0.80,\n      \"timeline\": \"ST/LT (6-12 months)\",\n      \"supporting_evidence\": [\n        \"Ripple joining Singapore MAS BLOOM sandbox for RLUSD trade finance\",\n        \"Hashdex diversified ETF options enabling institutional hedging\",\n        \"Corporate revenue decoupling from token price indicating B2B settlement adoption\"\n      ]\n    }\n  ],\n  \"cross_platform_patterns\": [\n    {\n      \"pattern\": \"Geopolitical Iran/Trump negotiations directly dictating intraday BTC price action\",\n      \"platforms\": [\"Benzinga\", \"CoinDesk\", \"Barrons\", \"Economic Times\"],\n      \"synchronization\": \"synchronized\"\n    },\n    {\n      \"pattern\": \"Whale accumulation data countering retail bearish sentiment\",\n      \"platforms\": [\"Finbold\", \"Cointelegraph\", \"Bitcoinist\", \"247WallSt\"],\n      \"synchronization\": \"synchronized\"\n    },\n    {\n      \"pattern\": \"AI security integration as next-phase infrastructure narrative\",\n      \"platforms\": [\"TechInAsia\", \"CoinDesk\", \"Benzinga\", \"Dev.to\"],\n      \"synchronization\": \"emerging\"\n    },\n    {\n      \"pattern\": \"Options expiry mechanics driving short-term liquidity flushes\",\n      \"platforms\": [\"CoinDesk\", \"Benzinga\", \"Nasdaq\", \"Business Standard\"],\n      \"synchronization\": \"synchronized\"\n    }\n  ],\n  \"summary\": \"Analysis of late-March 2026 crypto/financial data reveals a Markets-dominant entity heavily influenced by USAPop/GlobalPop geopolitical variables. The discourse is characterized by high cognitive dissonance between institutional accumulation (ETFs, whale flows, MAS sandbox) and retail capitulation (-60% XRP, fear metrics, leverage flushes). Memetic analysis shows the 'AI-Blockchain Integration' pattern reaching Stage 3 (Momentum), while the 'Crypto Safe-Haven' narrative fractures into Stage 4 (Critique) as macro correlation overrides digital gold theses. Key future leaks indicate AI-driven adversarial testing and real-world trade finance tokenization are the actual structural shifts, while quantum computing vulnerability is a dormant LT threat beginning to price in. Temporal anomalies highlight pre-announced kinetic infrastructure threats and retroactive narrative building masking real exchange dynamics. Cross-platform synchronization is strongest around options expiry mechanics and geopolitical risk transmission. Expect IM volatility driven by Iran outcomes/options cycles, ST structural consolidation via AI/regulatory frameworks, and LT paradigm shifts toward post-quantum cryptographic standards and stablecoin settlement dominance. The 'Herald' and 'Shadow' archetypes currently dominate, signaling a market in late-stage correction preparing for institutional utility normalization.\"\n}\n```",
  "error": "Failed to parse JSON"
}